screenValidator/__init__.py
screenValidator/version.py
screenvalidator-0.5.2.dist-info/licenses/LICENSE
screenvalidator-0.5.2.dist-info/METADATA
screenvalidator-0.5.2.dist-info/WHEEL
screenvalidator-0.5.2.dist-info/top_level.txt
screenvalidator-0.5.2.dist-info/RECORD
