Metadata-Version: 2.4
Name: screenValidator
Version: 0.5.2
Summary: Automated eye tracking data quality determination for screen-based eye trackers.
Home-page: https://github.com/dcnieho/screenValidator
Author: Diederick Niehorster
Author-email: diederick_c.niehorster@humlab.lu.se
License: MIT License
Project-URL: Source Code, https://github.com/dcnieho/screenValidator
Classifier: Programming Language :: Python :: 3.10
Classifier: License :: OSI Approved :: MIT License
Classifier: Operating System :: OS Independent
Requires-Python: >=3.10
License-File: LICENSE
Requires-Dist: numpy
Requires-Dist: pandas
Dynamic: author
Dynamic: author-email
Dynamic: classifier
Dynamic: description
Dynamic: description-content-type
Dynamic: home-page
Dynamic: license
Dynamic: license-file
Dynamic: project-url
Dynamic: requires-dist
Dynamic: requires-python
Dynamic: summary
